farm_ng/package/__init__.py
farm_ng/package/commands.py
farm_ng/package/package.py
farm_ng_package-0.1.5.dist-info/LICENSE
farm_ng_package-0.1.5.dist-info/METADATA
farm_ng_package-0.1.5.dist-info/WHEEL
farm_ng_package-0.1.5.dist-info/top_level.txt
farm_ng_package-0.1.5.dist-info/RECORD
