Metadata-Version: 2.2
Name: farm_ng_package
Version: 0.1.5
Home-page: https://github.com/farm-ng/farm-ng-pysetup
Download-URL: https://github.com/farm-ng/farm-ng-pysetup
Author: Farm-ng Inc.
Author-email: info@farm-ng.com
Keywords: robotics,open-source
Classifier: Development Status :: 4 - Beta
Classifier: Intended Audience :: Developers
Classifier: License :: OSI Approved :: Apache Software License
Classifier: Operating System :: OS Independent
Classifier: Programming Language :: Python :: 3
Classifier: Topic :: Software Development
Classifier: Framework :: Robot Framework
Requires-Python: >=3.6
License-File: LICENSE
Requires-Dist: grpcio-tools==1.64.1
Dynamic: download-url
